webpfield/__init__.py
webpfield/apps.py
webpfield/fields.py
webpfield/image_formats.py
webpfield/settings.py
webpfield/utils.py
webpfield/webp_storage.py
django_webpfield-0.1.0.dist-info/METADATA
django_webpfield-0.1.0.dist-info/WHEEL
django_webpfield-0.1.0.dist-info/licenses/LICENSE
django_webpfield-0.1.0.dist-info/RECORD
