Metadata-Version: 2.1
Name: django-webpfield
Version: 0.1.0
Summary: A simple library that convert any user uploaded images to webP format
Project-URL: github, https://github.com/ahmedwelhakim/django-webpfield/
Author-email: Ahmed Elhakim <ahmed.w.elhakim@gmail.com>
License: The MIT License (MIT)
License-File: LICENSE
Keywords: django,webp
Classifier: Environment :: Web Environment
Classifier: Framework :: Django
Classifier: Framework :: Django :: 4.2
Classifier: Intended Audience :: Developers
Classifier: License :: OSI Approved :: MIT License
Classifier: Operating System :: OS Independent
Classifier: Programming Language :: Python
Classifier: Programming Language :: Python :: 3
Classifier: Programming Language :: Python :: 3 :: Only
Classifier: Programming Language :: Python :: 3.10
Classifier: Programming Language :: Python :: 3.11
Classifier: Topic :: Internet :: WWW/HTTP
Classifier: Topic :: Multimedia :: Graphics :: Presentation
Classifier: Topic :: Software Development :: Libraries :: Application Frameworks
Classifier: Topic :: Software Development :: Libraries :: Python Modules
Requires-Python: >=3.11
Requires-Dist: django>=4.2
Requires-Dist: pillow>=9.5.0
